[{"lang": "Spanish", "links": "http://www.megavideo.com/?v=NOE9XBM2", "temp": "1", "serie": "G", "epi": "13", "type": "VerOnline"},
{"lang": "Spanish", "links": "http://www.megaupload.com/?d=WL5JL0OZ", "temp": "1", "serie": "G", "epi": "13", "type": "Descargar"},
{"lang": "Spanish", "links": "http://www.megavideo.com/?v=A97296SL", "temp": "1", "serie": "G", "epi": "08", "type": "VerOnline"},
{"lang": "Spanish", "links": "http://www.megavideo.com/?v=A97296SL", "temp": "1", "serie": "G", "epi": "08", "type": "VerOnline"},
{"lang": "Spanish", "links": "http://www.megaupload.com/?d=AUH7WO2C", "temp": "1", "serie": "G", "epi": "08", "type": "Descargar"},
{"lang": "Spanish", "links": "http://www.megaupload.com/?d=AUH7WO2C", "temp": "1", "serie": "G", "epi": "08", "type": "Descargar"},
{"lang": "Spanish", "links": "http://www.megavideo.com/?v=03XKIYPU", "temp": "1", "serie": "G", "epi": "13", "type": "VerOnline"},
{"lang": "Spanish", "links": "http://www.megaupload.com/?d=EZ0C6NMQ", "temp": "1", "serie": "G", "epi": "13", "type": "Descargar"},
{"lang": "Spanish", "links": "http://www.megavideo.com/?v=GKA358MK", "temp": "1", "serie": "G", "epi": "13", "type": "VerOnline"},
{"lang": "Spanish", "links": "http://www.megavideo.com/?v=GKA358MK", "temp": "1", "serie": "G", "epi": "13", "type": "VerOnline"},
{"lang": "Spanish", "links": "http://www.megaupload.com/?d=TYLMPN8J", "temp": "1", "serie": "G", "epi": "13", "type": "Descargar"},
{"lang": "Spanish", "links": "http://www.megaupload.com/?d=TYLMPN8J", "temp": "1", "serie": "G", "epi": "13", "type": "Descargar"},
{"lang": "Spanish", "links": "http://www.megavideo.com/?v=CV1SM7WX", "temp": "1", "serie": "G", "epi": "12", "type": "VerOnline"},
{"lang": "Spanish", "links": "http://www.megavideo.com/?v=CV1SM7WX", "temp": "1", "serie": "G", "epi": "12", "type": "VerOnline"},
{"lang": "Spanish", "links": "http://www.megaupload.com/?d=92FCUDB7", "temp": "1", "serie": "G", "epi": "12", "type": "Descargar"},
{"lang": "Spanish", "links": "http://www.megaupload.com/?d=92FCUDB7", "temp": "1", "serie": "G", "epi": "12", "type": "Descargar"},
{"lang": "Spanish", "links": "http://www.megavideo.com/?v=0D786NXG", "temp": "1", "serie": "G", "epi": "11", "type": "VerOnline"},
{"lang": "Spanish", "links": "http://www.megavideo.com/?v=4YP1W2AW", "temp": "1", "serie": "G", "epi": "11", "type": "VerOnline"},
{"lang": "Spanish", "links": "http://www.megaupload.com/?d=P7M8TYA3", "temp": "1", "serie": "G", "epi": "11", "type": "Descargar"},
{"lang": "Spanish", "links": "http://www.megaupload.com/?d=I02J3XC7", "temp": "1", "serie": "G", "epi": "11", "type": "Descargar"},
{"lang": "Spanish", "links": "http://www.megavideo.com/?v=4YP1W2AW", "temp": "1", "serie": "G", "epi": "10", "type": "VerOnline"},
{"lang": "Spanish", "links": "http://www.megavideo.com/?v=4YP1W2AW", "temp": "1", "serie": "G", "epi": "10", "type": "VerOnline"},
{"lang": "Spanish", "links": "http://www.megaupload.com/?d=I02J3XC7", "temp": "1", "serie": "G", "epi": "10", "type": "Descargar"},
{"lang": "Spanish", "links": "http://www.megaupload.com/?d=I02J3XC7", "temp": "1", "serie": "G", "epi": "10", "type": "Descargar"},
{"lang": "Spanish", "links": "http://www.megavideo.com/?v=DLHEJGWF", "temp": "1", "serie": "G", "epi": "09", "type": "VerOnline"},
{"lang": "Spanish", "links": "http://www.megavideo.com/?v=DLHEJGWF", "temp": "1", "serie": "G", "epi": "09", "type": "VerOnline"},
{"lang": "Spanish", "links": "http://www.megaupload.com/?d=F7SOPAMJ", "temp": "1", "serie": "G", "epi": "09", "type": "Descargar"},
{"lang": "Spanish", "links": "http://www.megaupload.com/?d=F7SOPAMJ", "temp": "1", "serie": "G", "epi": "09", "type": "Descargar"},
{"lang": "Spanish", "links": "http://www.megavideo.com/?v=2I1DA6KF", "temp": "1", "serie": "G", "epi": "08", "type": "VerOnline"},
{"lang": "Spanish", "links": "http://www.megavideo.com/?v=2I1DA6KF", "temp": "1", "serie": "G", "epi": "08", "type": "VerOnline"},
{"lang": "Spanish", "links": "http://www.megaupload.com/?d=91X5G4O7", "temp": "1", "serie": "G", "epi": "08", "type": "Descargar"},
{"lang": "Spanish", "links": "http://www.megaupload.com/?d=91X5G4O7", "temp": "1", "serie": "G", "epi": "08", "type": "Descargar"},
{"lang": "Spanish", "links": "http://www.megavideo.com/?v=FQDLH4BA", "temp": "1", "serie": "G", "epi": "07", "type": "VerOnline"},
{"lang": "Spanish", "links": "http://www.megavideo.com/?v=FQDLH4BA", "temp": "1", "serie": "G", "epi": "07", "type": "VerOnline"},
{"lang": "Spanish", "links": "http://www.megaupload.com/?d=PM12IS13", "temp": "1", "serie": "G", "epi": "07", "type": "Descargar"},
{"lang": "Spanish", "links": "http://www.megaupload.com/?d=PM12IS13", "temp": "1", "serie": "G", "epi": "07", "type": "Descargar"},
{"lang": "Spanish", "links": "http://www.megavideo.com/?v=3FB2XXST", "temp": "1", "serie": "G", "epi": "06", "type": "VerOnline"},
{"lang": "Spanish", "links": "http://www.megavideo.com/?v=3FB2XXST", "temp": "1", "serie": "G", "epi": "06", "type": "VerOnline"},
{"lang": "Spanish", "links": "http://www.megaupload.com/?d=SMYMPYJ9", "temp": "1", "serie": "G", "epi": "06", "type": "Descargar"},
{"lang": "Spanish", "links": "http://www.megaupload.com/?d=SMYMPYJ9", "temp": "1", "serie": "G", "epi": "06", "type": "Descargar"},
{"lang": "Spanish", "links": "http://www.megavideo.com/?v=160MTJPG", "temp": "1", "serie": "G", "epi": "05", "type": "VerOnline"},
{"lang": "Spanish", "links": "http://www.megavideo.com/?v=160MTJPG", "temp": "1", "serie": "G", "epi": "05", "type": "VerOnline"},
{"lang": "Spanish", "links": "http://www.megaupload.com/?d=LN2SVZGK", "temp": "1", "serie": "G", "epi": "05", "type": "Descargar"},
{"lang": "Spanish", "links": "http://www.megaupload.com/?d=LN2SVZGK", "temp": "1", "serie": "G", "epi": "05", "type": "Descargar"},
{"lang": "Spanish", "links": "http://www.megavideo.com/?v=MLVI86H4", "temp": "1", "serie": "G", "epi": "04", "type": "VerOnline"},
{"lang": "Spanish", "links": "http://www.megavideo.com/?v=MLVI86H4", "temp": "1", "serie": "G", "epi": "04", "type": "VerOnline"},
{"lang": "Spanish", "links": "http://www.megaupload.com/?d=ZZQGPIE2", "temp": "1", "serie": "G", "epi": "04", "type": "Descargar"},
{"lang": "Spanish", "links": "http://www.megaupload.com/?d=ZZQGPIE2", "temp": "1", "serie": "G", "epi": "04", "type": "Descargar"},
{"lang": "Spanish", "links": "http://www.megavideo.com/?v=TLWQURZ3", "temp": "1", "serie": "G", "epi": "03", "type": "VerOnline"},
{"lang": "Spanish", "links": "http://www.megavideo.com/?v=TLWQURZ3", "temp": "1", "serie": "G", "epi": "03", "type": "VerOnline"},
{"lang": "Spanish", "links": "http://www.megaupload.com/?d=5T7X9UHG", "temp": "1", "serie": "G", "epi": "03", "type": "Descargar"},
{"lang": "Spanish", "links": "http://www.megaupload.com/?d=5T7X9UHG", "temp": "1", "serie": "G", "epi": "03", "type": "Descargar"},
{"lang": "Spanish", "links": "http://www.megavideo.com/?v=6SWI8FD7", "temp": "1", "serie": "G", "epi": "02", "type": "VerOnline"},
{"lang": "Spanish", "links": "http://www.megavideo.com/?v=6SWI8FD7", "temp": "1", "serie": "G", "epi": "02", "type": "VerOnline"},
{"lang": "Spanish", "links": "http://www.megaupload.com/?d=F7SOPAMJ", "temp": "1", "serie": "G", "epi": "02", "type": "Descargar"},
{"lang": "Spanish", "links": "http://www.megaupload.com/?d=F7SOPAMJ", "temp": "1", "serie": "G", "epi": "02", "type": "Descargar"},
{"lang": "Spanish", "links": "http://www.megavideo.com/?v=6352U6UO", "temp": "1", "serie": "G", "epi": "01", "type": "VerOnline"},
{"lang": "Spanish", "links": "http://www.megavideo.com/?v=6352U6UO", "temp": "1", "serie": "G", "epi": "01", "type": "VerOnline"},
{"lang": "Spanish", "links": "http://www.megaupload.com/?d=3CTKYCWG", "temp": "1", "serie": "G", "epi": "01", "type": "Descargar"},
{"lang": "Spanish", "links": "http://www.megaupload.com/?d=3CTKYCWG", "temp": "1", "serie": "G", "epi": "01", "type": "Descargar"},
{"lang": "Spanish", "links": "http://www.megavideo.com/?v=F1B8VMCH", "temp": "1", "serie": "G", "epi": "12", "type": "VerOnline"},
{"lang": "Spanish", "links": "http://www.megaupload.com/?d=Q5SUGOOH", "temp": "1", "serie": "G", "epi": "12", "type": "Descargar"},
{"lang": "Spanish", "links": "http://www.megavideo.com/?v=N3P1YPO0", "temp": "1", "serie": "G", "epi": "11", "type": "VerOnline"},
{"lang": "Spanish", "links": "http://www.megaupload.com/?d=4BSLORY0", "temp": "1", "serie": "G", "epi": "11", "type": "Descargar"},
{"lang": "Spanish", "links": "http://www.megavideo.com/?v=67DGBSL8", "temp": "1", "serie": "G", "epi": "10", "type": "VerOnline"},
{"lang": "Spanish", "links": "http://www.megaupload.com/?d=5TTL88S4", "temp": "1", "serie": "G", "epi": "10", "type": "Descargar"},
{"lang": "Spanish", "links": "http://www.megavideo.com/?v=7UEDCRQ3", "temp": "1", "serie": "G", "epi": "09", "type": "VerOnline"},
{"lang": "Spanish", "links": "http://www.megaupload.com/?d=OK7QLTF6", "temp": "1", "serie": "G", "epi": "09", "type": "Descargar"},
{"lang": "Spanish", "links": "http://www.megavideo.com/?v=3VRVYR4D", "temp": "1", "serie": "G", "epi": "08", "type": "VerOnline"},
{"lang": "Spanish", "links": "http://www.megaupload.com/?d=6GR73CRM", "temp": "1", "serie": "G", "epi": "08", "type": "Descargar"},
{"lang": "Spanish", "links": "http://www.megavideo.com/?v=UCWECSX7", "temp": "1", "serie": "G", "epi": "06", "type": "VerOnline"},
{"lang": "Spanish", "links": "http://www.megaupload.com/?d=SM193POH", "temp": "1", "serie": "G", "epi": "06", "type": "Descargar"},
{"lang": "Spanish", "links": "http://www.megavideo.com/?v=ZHZJ4FNC", "temp": "1", "serie": "G", "epi": "05", "type": "VerOnline"},
{"lang": "Spanish", "links": "http://www.megaupload.com/?d=5YNW6Y62", "temp": "1", "serie": "G", "epi": "05", "type": "Descargar"},
{"lang": "Spanish", "links": "http://www.megavideo.com/?v=O8W6KLQB", "temp": "1", "serie": "G", "epi": "04", "type": "VerOnline"},
{"lang": "Spanish", "links": "http://www.megaupload.com/?d=CG3V3SQ6", "temp": "1", "serie": "G", "epi": "04", "type": "Descargar"},
{"lang": "Spanish", "links": "http://www.megavideo.com/?v=YWO86CBL", "temp": "1", "serie": "G", "epi": "03", "type": "VerOnline"},
{"lang": "Spanish", "links": "http://www.megaupload.com/?d=N2EA33C1", "temp": "1", "serie": "G", "epi": "03", "type": "Descargar"},
{"lang": "Spanish", "links": "http://www.megavideo.com/?v=BCXWXEMF", "temp": "1", "serie": "G", "epi": "02", "type": "VerOnline"},
{"lang": "Spanish", "links": "http://www.megaupload.com/?d=HJ2BMVCE", "temp": "1", "serie": "G", "epi": "02", "type": "Descargar"},
{"lang": "Spanish", "links": "http://www.megavideo.com/?v=JF0XGO90", "temp": "1", "serie": "G", "epi": "01", "type": "VerOnline"},
{"lang": "Spanish", "links": "http://www.megaupload.com/?d=JF0XGO90", "temp": "1", "serie": "G", "epi": "01", "type": "Descargar"},
{"lang": "Spanish", "links": "http://www.megavideo.com/?v=540XM6PN", "temp": "1", "serie": "G", "epi": "07", "type": "VerOnline"},
{"lang": "Spanish", "links": "http://www.megavideo.com/?v=540XM6PN", "temp": "1", "serie": "G", "epi": "07", "type": "VerOnline"},
{"lang": "Spanish", "links": "http://www.megaupload.com/?d=EIR9TJET", "temp": "1", "serie": "G", "epi": "07", "type": "Descargar"},
{"lang": "Spanish", "links": "http://www.megaupload.com/?d=EIR9TJET", "temp": "1", "serie": "G", "epi": "07", "type": "Descargar"},
{"lang": "Spanish", "links": "http://www.megavideo.com/?v=RXEU6OJV", "temp": "1", "serie": "G", "epi": "05", "type": "VerOnline"},
{"lang": "Spanish", "links": "http://www.megavideo.com/?v=RXEU6OJV", "temp": "1", "serie": "G", "epi": "05", "type": "VerOnline"},
{"lang": "Spanish", "links": "http://www.megaupload.com/?d=4KLFYZUT", "temp": "1", "serie": "G", "epi": "05", "type": "Descargar"},
{"lang": "Spanish", "links": "http://www.megaupload.com/?d=4KLFYZUT", "temp": "1", "serie": "G", "epi": "05", "type": "Descargar"},
{"lang": "Spanish", "links": "http://www.megavideo.com/?v=1RHBJ69T", "temp": "1", "serie": "G", "epi": "04", "type": "VerOnline"},
{"lang": "Spanish", "links": "http://www.megavideo.com/?v=1RHBJ69T", "temp": "1", "serie": "G", "epi": "04", "type": "VerOnline"},
{"lang": "Spanish", "links": "http://www.megaupload.com/?d=W4TQ6XVI", "temp": "1", "serie": "G", "epi": "04", "type": "Descargar"},
{"lang": "Spanish", "links": "http://www.megaupload.com/?d=W4TQ6XVI", "temp": "1", "serie": "G", "epi": "04", "type": "Descargar"},
{"lang": "Spanish", "links": "http://www.megavideo.com/?v=G50QZYDX", "temp": "1", "serie": "G", "epi": "03", "type": "VerOnline"},
{"lang": "Spanish", "links": "http://www.megavideo.com/?v=G50QZYDX", "temp": "1", "serie": "G", "epi": "03", "type": "VerOnline"},
{"lang": "Spanish", "links": "http://www.megaupload.com/?d=VRJWUHNZ", "temp": "1", "serie": "G", "epi": "03", "type": "Descargar"},
{"lang": "Spanish", "links": "http://www.megaupload.com/?d=VRJWUHNZ", "temp": "1", "serie": "G", "epi": "03", "type": "Descargar"},
{"lang": "Spanish", "links": "http://www.megavideo.com/?v=8Q59Q46O", "temp": "1", "serie": "G", "epi": "02", "type": "VerOnline"},
{"lang": "Spanish", "links": "http://www.megavideo.com/?v=8Q59Q46O", "temp": "1", "serie": "G", "epi": "02", "type": "VerOnline"},
{"lang": "Spanish", "links": "http://www.megaupload.com/?d=51J62VSX", "temp": "1", "serie": "G", "epi": "02", "type": "Descargar"},
{"lang": "Spanish", "links": "http://www.megaupload.com/?d=51J62VSX", "temp": "1", "serie": "G", "epi": "02", "type": "Descargar"},
{"lang": "Spanish", "links": "http://www.megavideo.com/?v=25QOO5OJ", "temp": "1", "serie": "G", "epi": "01", "type": "VerOnline"},
{"lang": "Spanish", "links": "http://www.megavideo.com/?v=25QOO5OJ", "temp": "1", "serie": "G", "epi": "01", "type": "VerOnline"},
{"lang": "Spanish", "links": "http://www.megaupload.com/?d=S3I95C0I", "temp": "1", "serie": "G", "epi": "01", "type": "Descargar"},
{"lang": "Spanish", "links": "http://www.megaupload.com/?d=S3I95C0I", "temp": "1", "serie": "G", "epi": "01", "type": "Descargar"},
{"lang": "Spanish", "links": "http://www.megavideo.com/?v=8PIR3IQG", "temp": "1", "serie": "G", "epi": "12", "type": "VerOnline"},
{"lang": "Spanish", "links": "http://www.megaupload.com/?d=ZS5BNJEZ", "temp": "1", "serie": "G", "epi": "12", "type": "Descargar"},
{"lang": "Spanish", "links": "http://www.megavideo.com/?v=EL11RVQS", "temp": "1", "serie": "G", "epi": "11", "type": "VerOnline"},
{"lang": "Spanish", "links": "http://www.megavideo.com/?v=2Q4AIAEO", "temp": "1", "serie": "G", "epi": "11", "type": "VerOnline"},
{"lang": "Spanish", "links": "http://www.megaupload.com/?d=S1K9BK2E", "temp": "1", "serie": "G", "epi": "11", "type": "Descargar"},
{"lang": "Spanish", "links": "http://www.megaupload.com/?d=VNJC0AQ4", "temp": "1", "serie": "G", "epi": "11", "type": "Descargar"},
{"lang": "Spanish", "links": "http://www.megavideo.com/?v=92RE2KY4", "temp": "1", "serie": "G", "epi": "10", "type": "VerOnline"},
{"lang": "Spanish", "links": "http://www.megaupload.com/?d=U877SDIX", "temp": "1", "serie": "G", "epi": "10", "type": "Descargar"},
{"lang": "Spanish", "links": "http://www.megavideo.com/?v=AWV58SHK", "temp": "1", "serie": "G", "epi": "09", "type": "VerOnline"},
{"lang": "Spanish", "links": "http://www.megaupload.com/?d=2PLK8GK2", "temp": "1", "serie": "G", "epi": "09", "type": "Descargar"},
{"lang": "Spanish", "links": "http://www.megavideo.com/?v=6XGBV4H8", "temp": "1", "serie": "G", "epi": "08", "type": "VerOnline"},
{"lang": "English", "links": "http://www.megavideo.com/?v=EHCHXQ5S", "temp": "1", "serie": "G", "epi": "08", "type": "VerOnline", "sublang": "Spanish"},
{"lang": "Spanish", "links": "http://www.megaupload.com/?d=Z13VTV2V", "temp": "1", "serie": "G", "epi": "08", "type": "Descargar"},
{"lang": "English", "links": "http://www.megaupload.com/?d=TSXBVDD7", "temp": "1", "serie": "G", "epi": "08", "type": "Descargar", "sublang": "Spanish"},
{"lang": "Spanish", "links": "http://www.megavideo.com/?v=SE2V5CHD", "temp": "1", "serie": "G", "epi": "07", "type": "VerOnline"},
{"lang": "English", "links": "http://www.megavideo.com/?v=EA4W2BJM", "temp": "1", "serie": "G", "epi": "07", "type": "VerOnline", "sublang": "Spanish"},
{"lang": "Spanish", "links": "http://www.megaupload.com/?d=CRBXITML", "temp": "1", "serie": "G", "epi": "07", "type": "Descargar"},
{"lang": "English", "links": "http://www.megaupload.com/?d=389UBVOX", "temp": "1", "serie": "G", "epi": "07", "type": "Descargar", "sublang": "Spanish"},
{"lang": "Spanish", "links": "http://www.megavideo.com/?v=EELRUEQ0", "temp": "1", "serie": "G", "epi": "06", "type": "VerOnline"},
{"lang": "Spanish", "links": "http://www.megavideo.com/?v=EELRUEQ0", "temp": "1", "serie": "G", "epi": "06", "type": "VerOnline"},
{"lang": "Spanish", "links": "http://www.megaupload.com/?d=389UBVOX", "temp": "1", "serie": "G", "epi": "06", "type": "Descargar"},
{"lang": "Spanish", "links": "http://www.megaupload.com/?d=389UBVOX", "temp": "1", "serie": "G", "epi": "06", "type": "Descargar"},
{"lang": "Spanish", "links": "http://www.megavideo.com/?v=3DWISUOX", "temp": "1", "serie": "G", "epi": "05", "type": "VerOnline"},
{"lang": "English", "links": "http://www.megavideo.com/?v=TU8TZDKZ", "temp": "1", "serie": "G", "epi": "05", "type": "VerOnline", "sublang": "Spanish"},
{"lang": "Spanish", "links": "http://www.megaupload.com/?d=4CJZEDJL", "temp": "1", "serie": "G", "epi": "05", "type": "Descargar"},
{"lang": "English", "links": "http://www.megaupload.com/?d=YBLYPHGD", "temp": "1", "serie": "G", "epi": "05", "type": "Descargar", "sublang": "Spanish"},
{"lang": "Spanish", "links": "http://www.megavideo.com/?v=PNAUFANR", "temp": "1", "serie": "G", "epi": "04", "type": "VerOnline"},
{"lang": "Spanish", "links": "http://www.megaupload.com/?d=HESB6L77", "temp": "1", "serie": "G", "epi": "04", "type": "Descargar"},
{"lang": "Spanish", "links": "http://www.megavideo.com/?v=9KVRPUOQ", "temp": "1", "serie": "G", "epi": "03", "type": "VerOnline"},
{"lang": "Spanish", "links": "http://www.megaupload.com/?d=BKDS6SJ4", "temp": "1", "serie": "G", "epi": "03", "type": "Descargar"},
{"lang": "Spanish", "links": "http://www.megavideo.com/?v=4FCITEGI", "temp": "1", "serie": "G", "epi": "02", "type": "VerOnline"},
{"lang": "English", "links": "http://www.megavideo.com/?v=EGI50J6A", "temp": "1", "serie": "G", "epi": "02", "type": "VerOnline", "sublang": "Spanish"},
{"lang": "Spanish", "links": "http://www.megaupload.com/?d=3THKT0JD", "temp": "1", "serie": "G", "epi": "02", "type": "Descargar"},
{"lang": "English", "links": "http://www.megaupload.com/?d=512S59CG", "temp": "1", "serie": "G", "epi": "02", "type": "Descargar", "sublang": "Spanish"},
{"lang": "Spanish", "links": "http://www.megavideo.com/?v=Z3LFA0P6", "temp": "1", "serie": "G", "epi": "01", "type": "VerOnline"},
{"lang": "English", "links": "http://www.megavideo.com/?v=KJLTD0Z9", "temp": "1", "serie": "G", "epi": "01", "type": "VerOnline", "sublang": "Spanish"},
{"lang": "Spanish", "links": "http://www.megaupload.com/?d=4IHQDS77", "temp": "1", "serie": "G", "epi": "01", "type": "Descargar"},
{"lang": "English", "links": "http://www.megaupload.com/?d=9SCHD1V6", "temp": "1", "serie": "G", "epi": "01", "type": "Descargar", "sublang": "Spanish"},
{"lang": "Spanish", "links": "http://www.megavideo.com/?v=P1GFIGT0", "temp": "1", "serie": "G", "epi": "01", "type": "VerOnline"},
{"lang": "Spanish", "links": "http://www.megavideo.com/?v=P1GFIGT0", "temp": "1", "serie": "G", "epi": "01", "type": "VerOnline"},
{"lang": "Spanish", "links": "http://www.megaupload.com/?d=4MBMQWJ8", "temp": "1", "serie": "G", "epi": "01", "type": "Descargar"},
{"lang": "Spanish", "links": "http://www.megaupload.com/?d=4MBMQWJ8", "temp": "1", "serie": "G", "epi": "01", "type": "Descargar"},
{"lang": "English", "links": "http://www.megavideo.com/?v=YBH3F6EB", "temp": "2", "serie": "G", "epi": "04", "type": "VerOnline", "sublang": "Spanish"},
{"lang": "English", "links": "http://www.megavideo.com/?v=YBH3F6EB", "temp": "2", "serie": "G", "epi": "04", "type": "VerOnline", "sublang": "Spanish"},
{"lang": "English", "links": "http://www.megaupload.com/?d=NWV6GA79", "temp": "2", "serie": "G", "epi": "04", "type": "Descargar", "sublang": "Spanish"},
{"lang": "English", "links": "http://www.megaupload.com/?d=NWV6GA79", "temp": "2", "serie": "G", "epi": "04", "type": "Descargar", "sublang": "Spanish"},
{"lang": "English", "links": "http://www.megavideo.com/?v=HZV28E4K", "temp": "2", "serie": "G", "epi": "03", "type": "VerOnline", "sublang": "Spanish"},
{"lang": "English", "links": "http://www.megavideo.com/?v=HZV28E4K", "temp": "2", "serie": "G", "epi": "03", "type": "VerOnline", "sublang": "Spanish"},
{"lang": "English", "links": "http://www.megaupload.com/?d=5HPCV3Z5", "temp": "2", "serie": "G", "epi": "03", "type": "Descargar", "sublang": "Spanish"},
{"lang": "English", "links": "http://www.megaupload.com/?d=5HPCV3Z5", "temp": "2", "serie": "G", "epi": "03", "type": "Descargar", "sublang": "Spanish"},
{"lang": "English", "links": "http://www.megavideo.com/?v=NEJOUE2T", "temp": "4", "serie": "G", "epi": "05", "type": "VerOnline", "sublang": "Spanish"},
{"lang": "English", "links": "http://www.megavideo.com/?v=NEJOUE2T", "temp": "4", "serie": "G", "epi": "05", "type": "VerOnline", "sublang": "Spanish"},
{"lang": "English", "links": "http://www.megaupload.com/?d=JPMYUZ2M", "temp": "4", "serie": "G", "epi": "05", "type": "Descargar", "sublang": "Spanish"},
{"lang": "English", "links": "http://www.megaupload.com/?d=JPMYUZ2M", "temp": "4", "serie": "G", "epi": "05", "type": "Descargar", "sublang": "Spanish"},
{"lang": "English", "links": "http://www.megavideo.com/?v=W26HQP1E", "temp": "4", "serie": "G", "epi": "04", "type": "VerOnline", "sublang": "Spanish"},
{"lang": "English", "links": "http://www.megavideo.com/?v=W26HQP1E", "temp": "4", "serie": "G", "epi": "04", "type": "VerOnline", "sublang": "Spanish"},
{"lang": "English", "links": "http://www.megaupload.com/?d=9XOV8DR0", "temp": "4", "serie": "G", "epi": "04", "type": "Descargar", "sublang": "Spanish"},
{"lang": "English", "links": "http://www.megaupload.com/?d=9XOV8DR0", "temp": "4", "serie": "G", "epi": "04", "type": "Descargar", "sublang": "Spanish"},
{"lang": "English", "links": "http://www.megavideo.com/?v=PT64Z65O", "temp": "4", "serie": "G", "epi": "03", "type": "VerOnline", "sublang": "Spanish"},
{"lang": "English", "links": "http://www.megavideo.com/?v=PT64Z65O", "temp": "4", "serie": "G", "epi": "03", "type": "VerOnline", "sublang": "Spanish"},
{"lang": "English", "links": "http://www.megaupload.com/?d=MIVJUZ3P", "temp": "4", "serie": "G", "epi": "03", "type": "Descargar", "sublang": "Spanish"},
{"lang": "English", "links": "http://www.megaupload.com/?d=MIVJUZ3P", "temp": "4", "serie": "G", "epi": "03", "type": "Descargar", "sublang": "Spanish"},
{"lang": "English", "links": "http://www.megavideo.com/?v=IYQ53XQ1", "temp": "4", "serie": "G", "epi": "02", "type": "VerOnline", "sublang": "Spanish"},
{"lang": "English", "links": "http://www.megavideo.com/?v=IYQ53XQ1", "temp": "4", "serie": "G", "epi": "02", "type": "VerOnline", "sublang": "Spanish"},
{"lang": "English", "links": "http://www.megaupload.com/?d=HRE8BRMC", "temp": "4", "serie": "G", "epi": "02", "type": "Descargar", "sublang": "Spanish"},
{"lang": "English", "links": "http://www.megaupload.com/?d=HRE8BRMC", "temp": "4", "serie": "G", "epi": "02", "type": "Descargar", "sublang": "Spanish"},
{"lang": "English", "links": "http://www.megavideo.com/?v=LTUM1JS9", "temp": "4", "serie": "G", "epi": "01", "type": "VerOnline", "sublang": "Spanish"},
{"lang": "English", "links": "http://www.megavideo.com/?v=LTUM1JS9", "temp": "4", "serie": "G", "epi": "01", "type": "VerOnline", "sublang": "Spanish"},
{"lang": "English", "links": "http://www.megaupload.com/?d=SX9WNUV7", "temp": "4", "serie": "G", "epi": "01", "type": "Descargar", "sublang": "Spanish"},
{"lang": "English", "links": "http://www.megaupload.com/?d=SX9WNUV7", "temp": "4", "serie": "G", "epi": "01", "type": "Descargar", "sublang": "Spanish"},
{"lang": "Spanish", "links": "http://www.megavideo.com/?v=774TX2ME", "temp": "3", "serie": "G", "epi": "22", "type": "VerOnline"},
{"lang": "Spanish", "links": "http://www.megavideo.com/?v=774TX2ME", "temp": "3", "serie": "G", "epi": "22", "type": "VerOnline"},
{"lang": "Spanish", "links": "http://www.megaupload.com/?d=RJE6N9B7", "temp": "3", "serie": "G", "epi": "22", "type": "Descargar"},
{"lang": "Spanish", "links": "http://www.megaupload.com/?d=RJE6N9B7", "temp": "3", "serie": "G", "epi": "22", "type": "Descargar"},
{"lang": "Spanish", "links": "http://www.megavideo.com/?v=DAMSN2BV", "temp": "3", "serie": "G", "epi": "21", "type": "VerOnline"},
{"lang": "Spanish", "links": "http://www.megavideo.com/?v=06V9GHV4", "temp": "3", "serie": "G", "epi": "21", "type": "VerOnline"},
{"lang": "Spanish", "links": "http://www.megaupload.com/?d=VUB2UFJN", "temp": "3", "serie": "G", "epi": "21", "type": "Descargar"},
{"lang": "Spanish", "links": "http://www.megaupload.com/?d=K7O8SHWT", "temp": "3", "serie": "G", "epi": "21", "type": "Descargar"},
{"lang": "Spanish", "links": "http://www.megavideo.com/?v=RVBTZ1ES", "temp": "3", "serie": "G", "epi": "20", "type": "VerOnline"},
{"lang": "Spanish", "links": "http://www.megavideo.com/?v=RVBTZ1ES", "temp": "3", "serie": "G", "epi": "20", "type": "VerOnline"},
{"lang": "Spanish", "links": "http://www.megaupload.com/?d=J9DMMQQH", "temp": "3", "serie": "G", "epi": "20", "type": "Descargar"},
{"lang": "Spanish", "links": "http://www.megaupload.com/?d=J9DMMQQH", "temp": "3", "serie": "G", "epi": "20", "type": "Descargar"},
{"lang": "Spanish", "links": "http://www.megavideo.com/?v=UG1XZRN4", "temp": "3", "serie": "G", "epi": "19", "type": "VerOnline"},
{"lang": "Spanish", "links": "http://www.megavideo.com/?v=UG1XZRN4", "temp": "3", "serie": "G", "epi": "19", "type": "VerOnline"},
{"lang": "Spanish", "links": "http://www.megaupload.com/?d=0PO28X99", "temp": "3", "serie": "G", "epi": "19", "type": "Descargar"},
{"lang": "Spanish", "links": "http://www.megaupload.com/?d=0PO28X99", "temp": "3", "serie": "G", "epi": "19", "type": "Descargar"},
{"lang": "Spanish", "links": "http://www.megavideo.com/?v=DGX7L6PE", "temp": "3", "serie": "G", "epi": "18", "type": "VerOnline"},
{"lang": "Spanish", "links": "http://www.megavideo.com/?v=DGX7L6PE", "temp": "3", "serie": "G", "epi": "18", "type": "VerOnline"},
{"lang": "Spanish", "links": "http://www.megaupload.com/?d=76L239OG", "temp": "3", "serie": "G", "epi": "18", "type": "Descargar"},
{"lang": "Spanish", "links": "http://www.megaupload.com/?d=76L239OG", "temp": "3", "serie": "G", "epi": "18", "type": "Descargar"},
{"lang": "Spanish", "links": "http://www.megavideo.com/?v=BOPAAXZI", "temp": "3", "serie": "G", "epi": "17", "type": "VerOnline"},
{"lang": "Spanish", "links": "http://www.megavideo.com/?v=BOPAAXZI", "temp": "3", "serie": "G", "epi": "17", "type": "VerOnline"},
{"lang": "Spanish", "links": "http://www.megaupload.com/?d=53OE5UY9", "temp": "3", "serie": "G", "epi": "17", "type": "Descargar"},
{"lang": "Spanish", "links": "http://www.megaupload.com/?d=53OE5UY9", "temp": "3", "serie": "G", "epi": "17", "type": "Descargar"},
{"lang": "Spanish", "links": "http://www.megavideo.com/?v=3TGVA203", "temp": "3", "serie": "G", "epi": "16", "type": "VerOnline"},
{"lang": "Spanish", "links": "http://www.megavideo.com/?v=3TGVA203", "temp": "3", "serie": "G", "epi": "16", "type": "VerOnline"},
{"lang": "Spanish", "links": "http://www.megaupload.com/?d=BN3HLKO1", "temp": "3", "serie": "G", "epi": "16", "type": "Descargar"},
{"lang": "Spanish", "links": "http://www.megaupload.com/?d=BN3HLKO1", "temp": "3", "serie": "G", "epi": "16", "type": "Descargar"},
{"lang": "Spanish", "links": "http://www.megavideo.com/?v=VM4AN6VD", "temp": "3", "serie": "G", "epi": "15", "type": "VerOnline"},
{"lang": "Spanish", "links": "http://www.megavideo.com/?v=726M2HTE", "temp": "3", "serie": "G", "epi": "15", "type": "VerOnline"},
{"lang": "Spanish", "links": "http://www.megaupload.com/?d=UOZSP2XL", "temp": "3", "serie": "G", "epi": "15", "type": "Descargar"},
{"lang": "Spanish", "links": "http://www.megaupload.com/?d=UOZSP2XL", "temp": "3", "serie": "G", "epi": "15", "type": "Descargar"},
{"lang": "Spanish", "links": "http://www.megavideo.com/?v=QB96RO4P", "temp": "3", "serie": "G", "epi": "14", "type": "VerOnline"},
{"lang": "Spanish", "links": "http://www.megavideo.com/?v=QB96RO4P", "temp": "3", "serie": "G", "epi": "14", "type": "VerOnline"},
{"lang": "Spanish", "links": "http://www.megaupload.com/?d=F40RJDZK", "temp": "3", "serie": "G", "epi": "14", "type": "Descargar"},
{"lang": "Spanish", "links": "http://www.megaupload.com/?d=F40RJDZK", "temp": "3", "serie": "G", "epi": "14", "type": "Descargar"},
{"lang": "Spanish", "links": "http://www.megavideo.com/?v=3BEECXKP", "temp": "3", "serie": "G", "epi": "13", "type": "VerOnline"},
{"lang": "Spanish", "links": "http://www.megavideo.com/?v=3BEECXKP", "temp": "3", "serie": "G", "epi": "13", "type": "VerOnline"},
{"lang": "Spanish", "links": "http://www.megaupload.com/?d=G17RTZKD", "temp": "3", "serie": "G", "epi": "13", "type": "Descargar"},
{"lang": "Spanish", "links": "http://www.megaupload.com/?d=G17RTZKD", "temp": "3", "serie": "G", "epi": "13", "type": "Descargar"},
{"lang": "Spanish", "links": "http://www.megavideo.com/?v=WEVJ172B", "temp": "3", "serie": "G", "epi": "12", "type": "VerOnline"},
{"lang": "Spanish", "links": "http://www.megavideo.com/?v=WEVJ172B", "temp": "3", "serie": "G", "epi": "12", "type": "VerOnline"},
{"lang": "Spanish", "links": "http://www.megaupload.com/?d=5YDUSE4R", "temp": "3", "serie": "G", "epi": "12", "type": "Descargar"},
{"lang": "Spanish", "links": "http://www.megaupload.com/?d=5YDUSE4R", "temp": "3", "serie": "G", "epi": "12", "type": "Descargar"},
{"lang": "Spanish", "links": "http://www.megavideo.com/?v=0P4SWV8Z", "temp": "3", "serie": "G", "epi": "11", "type": "VerOnline"},
{"lang": "Spanish", "links": "http://www.megavideo.com/?v=0P4SWV8Z", "temp": "3", "serie": "G", "epi": "11", "type": "VerOnline"},
{"lang": "Spanish", "links": "http://www.megaupload.com/?d=O1FUNP8N", "temp": "3", "serie": "G", "epi": "11", "type": "Descargar"},
{"lang": "Spanish", "links": "http://www.megaupload.com/?d=O1FUNP8N", "temp": "3", "serie": "G", "epi": "11", "type": "Descargar"},
{"lang": "Spanish", "links": "http://www.megavideo.com/?v=IJQ0CWX1", "temp": "3", "serie": "G", "epi": "10", "type": "VerOnline"},
{"lang": "Spanish", "links": "http://www.megavideo.com/?v=IJQ0CWX1", "temp": "3", "serie": "G", "epi": "10", "type": "VerOnline"},
{"lang": "Spanish", "links": "http://www.megaupload.com/?d=82E0U7ID", "temp": "3", "serie": "G", "epi": "10", "type": "Descargar"},
{"lang": "Spanish", "links": "http://www.megaupload.com/?d=82E0U7ID", "temp": "3", "serie": "G", "epi": "10", "type": "Descargar"},
{"lang": "Spanish", "links": "http://www.megavideo.com/?v=L85KWAL6", "temp": "3", "serie": "G", "epi": "09", "type": "VerOnline"},
{"lang": "Spanish", "links": "http://www.megavideo.com/?v=L85KWAL6", "temp": "3", "serie": "G", "epi": "09", "type": "VerOnline"},
{"lang": "Spanish", "links": "http://www.megaupload.com/?d=7T65QS8P", "temp": "3", "serie": "G", "epi": "09", "type": "Descargar"},
{"lang": "Spanish", "links": "http://www.megaupload.com/?d=7T65QS8P", "temp": "3", "serie": "G", "epi": "09", "type": "Descargar"},
{"lang": "Spanish", "links": "http://www.megavideo.com/?v=V5NPCL6P", "temp": "3", "serie": "G", "epi": "08", "type": "VerOnline"},
{"lang": "Spanish", "links": "http://www.megavideo.com/?v=V5NPCL6P", "temp": "3", "serie": "G", "epi": "08", "type": "VerOnline"},
{"lang": "Spanish", "links": "http://www.megaupload.com/?d=KM18AYRE", "temp": "3", "serie": "G", "epi": "08", "type": "Descargar"},
{"lang": "Spanish", "links": "http://www.megaupload.com/?d=KM18AYRE", "temp": "3", "serie": "G", "epi": "08", "type": "Descargar"},
{"lang": "Spanish", "links": "http://www.megavideo.com/?v=ENPJXC10", "temp": "3", "serie": "G", "epi": "07", "type": "VerOnline"},
{"lang": "Spanish", "links": "http://www.megavideo.com/?v=ENPJXC10", "temp": "3", "serie": "G", "epi": "07", "type": "VerOnline"},
{"lang": "Spanish", "links": "http://www.megaupload.com/?d=0ACVNMKP", "temp": "3", "serie": "G", "epi": "07", "type": "Descargar"},
{"lang": "Spanish", "links": "http://www.megaupload.com/?d=0ACVNMKP", "temp": "3", "serie": "G", "epi": "07", "type": "Descargar"},
{"lang": "Spanish", "links": "http://www.megavideo.com/?v=0B4CQLM4", "temp": "3", "serie": "G", "epi": "06", "type": "VerOnline"},
{"lang": "Spanish", "links": "http://www.megavideo.com/?v=0B4CQLM4", "temp": "3", "serie": "G", "epi": "06", "type": "VerOnline"},
{"lang": "Spanish", "links": "http://www.megaupload.com/?d=FVYN2E9Y", "temp": "3", "serie": "G", "epi": "06", "type": "Descargar"},
{"lang": "Spanish", "links": "http://www.megaupload.com/?d=FVYN2E9Y", "temp": "3", "serie": "G", "epi": "06", "type": "Descargar"},
{"lang": "Spanish", "links": "http://www.megavideo.com/?v=Z07Z1Z65", "temp": "3", "serie": "G", "epi": "05", "type": "VerOnline"},
{"lang": "Spanish", "links": "http://www.megavideo.com/?v=Z07Z1Z65", "temp": "3", "serie": "G", "epi": "05", "type": "VerOnline"},
{"lang": "Spanish", "links": "http://www.megaupload.com/?d=PYP3BFVO", "temp": "3", "serie": "G", "epi": "05", "type": "Descargar"},
{"lang": "Spanish", "links": "http://www.megaupload.com/?d=PYP3BFVO", "temp": "3", "serie": "G", "epi": "05", "type": "Descargar"},
{"lang": "Spanish", "links": "http://www.megavideo.com/?v=63NTQVP3", "temp": "3", "serie": "G", "epi": "04", "type": "VerOnline"},
{"lang": "Spanish", "links": "http://www.megavideo.com/?v=63NTQVP3", "temp": "3", "serie": "G", "epi": "04", "type": "VerOnline"},
{"lang": "Spanish", "links": "http://www.megaupload.com/?d=IDVW5OYL", "temp": "3", "serie": "G", "epi": "04", "type": "Descargar"},
{"lang": "Spanish", "links": "http://www.megaupload.com/?d=IDVW5OYL", "temp": "3", "serie": "G", "epi": "04", "type": "Descargar"},
{"lang": "Spanish", "links": "http://www.megavideo.com/?v=23QFXF6I", "temp": "3", "serie": "G", "epi": "03", "type": "VerOnline"},
{"lang": "Spanish", "links": "http://www.megavideo.com/?v=23QFXF6I", "temp": "3", "serie": "G", "epi": "03", "type": "VerOnline"},
{"lang": "Spanish", "links": "http://www.megaupload.com/?d=7V8VNCFU", "temp": "3", "serie": "G", "epi": "03", "type": "Descargar"},
{"lang": "Spanish", "links": "http://www.megaupload.com/?d=7V8VNCFU", "temp": "3", "serie": "G", "epi": "03", "type": "Descargar"},
{"lang": "Spanish", "links": "http://www.megavideo.com/?v=DQ4RH4ZH", "temp": "3", "serie": "G", "epi": "02", "type": "VerOnline"},
{"lang": "Spanish", "links": "http://www.megavideo.com/?v=DQ4RH4ZH", "temp": "3", "serie": "G", "epi": "02", "type": "VerOnline"},
{"lang": "Spanish", "links": "http://www.megaupload.com/?d=DKG46RP1", "temp": "3", "serie": "G", "epi": "02", "type": "Descargar"},
{"lang": "Spanish", "links": "http://www.megaupload.com/?d=DKG46RP1", "temp": "3", "serie": "G", "epi": "02", "type": "Descargar"},
{"lang": "Spanish", "links": "http://www.megavideo.com/?v=7WOM0UB6", "temp": "3", "serie": "G", "epi": "01", "type": "VerOnline"},
{"lang": "Spanish", "links": "http://www.megavideo.com/?v=7WOM0UB6", "temp": "3", "serie": "G", "epi": "01", "type": "VerOnline"},
{"lang": "Spanish", "links": "http://www.megaupload.com/?d=28HX2ENU", "temp": "3", "serie": "G", "epi": "01", "type": "Descargar"},
{"lang": "Spanish", "links": "http://www.megaupload.com/?d=28HX2ENU", "temp": "3", "serie": "G", "epi": "01", "type": "Descargar"},
{"lang": "Spanish", "links": "http://www.megavideo.com/?v=R8OPQO76", "temp": "2", "serie": "G", "epi": "25", "type": "VerOnline"},
{"lang": "Spanish", "links": "http://www.megavideo.com/?v=R8OPQO76", "temp": "2", "serie": "G", "epi": "25", "type": "VerOnline"},
{"lang": "Spanish", "links": "http://www.megaupload.com/?d=OVPP52U0", "temp": "2", "serie": "G", "epi": "25", "type": "Descargar"},
{"lang": "Spanish", "links": "http://www.megaupload.com/?d=OVPP52U0", "temp": "2", "serie": "G", "epi": "25", "type": "Descargar"},
{"lang": "Spanish", "links": "http://www.megavideo.com/?v=FZ4QD78P", "temp": "2", "serie": "G", "epi": "24", "type": "VerOnline"},
{"lang": "Spanish", "links": "http://www.megavideo.com/?v=FZ4QD78P", "temp": "2", "serie": "G", "epi": "24", "type": "VerOnline"},
{"lang": "Spanish", "links": "http://www.megaupload.com/?d=PFEYTVJO", "temp": "2", "serie": "G", "epi": "24", "type": "Descargar"},
{"lang": "Spanish", "links": "http://www.megaupload.com/?d=PFEYTVJO", "temp": "2", "serie": "G", "epi": "24", "type": "Descargar"},
{"lang": "Spanish", "links": "http://www.megavideo.com/?v=ONADJLD1", "temp": "2", "serie": "G", "epi": "23", "type": "VerOnline"},
{"lang": "Spanish", "links": "http://www.megavideo.com/?v=ONADJLD1", "temp": "2", "serie": "G", "epi": "23", "type": "VerOnline"},
{"lang": "Spanish", "links": "http://www.megaupload.com/?d=IBD8JKSG", "temp": "2", "serie": "G", "epi": "23", "type": "Descargar"},
{"lang": "Spanish", "links": "http://www.megaupload.com/?d=IBD8JKSG", "temp": "2", "serie": "G", "epi": "23", "type": "Descargar"},
{"lang": "Spanish", "links": "http://www.megavideo.com/?v=XKYN2V02", "temp": "2", "serie": "G", "epi": "22", "type": "VerOnline"},
{"lang": "Spanish", "links": "http://www.megavideo.com/?v=XKYN2V02", "temp": "2", "serie": "G", "epi": "22", "type": "VerOnline"},
{"lang": "Spanish", "links": "http://www.megaupload.com/?d=YK9DKMB6", "temp": "2", "serie": "G", "epi": "22", "type": "Descargar"},
{"lang": "Spanish", "links": "http://www.megaupload.com/?d=YK9DKMB6", "temp": "2", "serie": "G", "epi": "22", "type": "Descargar"},
{"lang": "Spanish", "links": "http://www.megavideo.com/?v=DP0ZQJU2", "temp": "2", "serie": "G", "epi": "21", "type": "VerOnline"},
{"lang": "Spanish", "links": "http://www.megavideo.com/?v=DP0ZQJU2", "temp": "2", "serie": "G", "epi": "21", "type": "VerOnline"},
{"lang": "Spanish", "links": "http://www.megaupload.com/?d=WCX7SLZ2", "temp": "2", "serie": "G", "epi": "21", "type": "Descargar"},
{"lang": "Spanish", "links": "http://www.megaupload.com/?d=WCX7SLZ2", "temp": "2", "serie": "G", "epi": "21", "type": "Descargar"},
{"lang": "Spanish", "links": "http://www.megavideo.com/?v=STMCCMP7", "temp": "2", "serie": "G", "epi": "20", "type": "VerOnline"},
{"lang": "Spanish", "links": "http://www.megavideo.com/?v=STMCCMP7", "temp": "2", "serie": "G", "epi": "20", "type": "VerOnline"},
{"lang": "Spanish", "links": "http://www.megaupload.com/?d=UHOAW8W1", "temp": "2", "serie": "G", "epi": "20", "type": "Descargar"},
{"lang": "Spanish", "links": "http://www.megaupload.com/?d=UHOAW8W1", "temp": "2", "serie": "G", "epi": "20", "type": "Descargar"},
{"lang": "Spanish", "links": "http://www.megavideo.com/?v=FV26ID5B", "temp": "2", "serie": "G", "epi": "19", "type": "VerOnline"},
{"lang": "Spanish", "links": "http://www.megavideo.com/?v=FV26ID5B", "temp": "2", "serie": "G", "epi": "19", "type": "VerOnline"},
{"lang": "Spanish", "links": "http://www.megaupload.com/?d=9BMRNBK9", "temp": "2", "serie": "G", "epi": "19", "type": "Descargar"},
{"lang": "Spanish", "links": "http://www.megaupload.com/?d=9BMRNBK9", "temp": "2", "serie": "G", "epi": "19", "type": "Descargar"},
{"lang": "Spanish", "links": "http://www.megavideo.com/?v=JRUI7K20", "temp": "2", "serie": "G", "epi": "18", "type": "VerOnline"},
{"lang": "Spanish", "links": "http://www.megavideo.com/?v=JRUI7K20", "temp": "2", "serie": "G", "epi": "18", "type": "VerOnline"},
{"lang": "Spanish", "links": "http://www.megaupload.com/?d=20K5RHTP", "temp": "2", "serie": "G", "epi": "18", "type": "Descargar"},
{"lang": "Spanish", "links": "http://www.megaupload.com/?d=20K5RHTP", "temp": "2", "serie": "G", "epi": "18", "type": "Descargar"},
{"lang": "Spanish", "links": "http://www.megavideo.com/?v=LZ66VNWA", "temp": "2", "serie": "G", "epi": "17", "type": "VerOnline"},
{"lang": "Spanish", "links": "http://www.megavideo.com/?v=LZ66VNWA", "temp": "2", "serie": "G", "epi": "17", "type": "VerOnline"},
{"lang": "Spanish", "links": "http://www.megaupload.com/?d=4ADD3VST", "temp": "2", "serie": "G", "epi": "17", "type": "Descargar"},
{"lang": "Spanish", "links": "http://www.megaupload.com/?d=4ADD3VST", "temp": "2", "serie": "G", "epi": "17", "type": "Descargar"},
{"lang": "Spanish", "links": "http://www.megavideo.com/?v=Y3W3J3IG", "temp": "2", "serie": "G", "epi": "16", "type": "VerOnline"},
{"lang": "Spanish", "links": "http://www.megavideo.com/?v=Y3W3J3IG", "temp": "2", "serie": "G", "epi": "16", "type": "VerOnline"},
{"lang": "Spanish", "links": "http://www.megaupload.com/?d=FYT2RJBL", "temp": "2", "serie": "G", "epi": "16", "type": "Descargar"},
{"lang": "Spanish", "links": "http://www.megaupload.com/?d=FYT2RJBL", "temp": "2", "serie": "G", "epi": "16", "type": "Descargar"},
{"lang": "Spanish", "links": "http://www.megavideo.com/?v=SHLD2AQI", "temp": "2", "serie": "G", "epi": "15", "type": "VerOnline"},
{"lang": "Spanish", "links": "http://www.megavideo.com/?v=SHLD2AQI", "temp": "2", "serie": "G", "epi": "15", "type": "VerOnline"},
{"lang": "Spanish", "links": "http://www.megaupload.com/?d=NB2C1818", "temp": "2", "serie": "G", "epi": "15", "type": "Descargar"},
{"lang": "Spanish", "links": "http://www.megaupload.com/?d=NB2C1818", "temp": "2", "serie": "G", "epi": "15", "type": "Descargar"},
{"lang": "Spanish", "links": "http://www.megavideo.com/?v=H4ZILSZS", "temp": "2", "serie": "G", "epi": "14", "type": "VerOnline"},
{"lang": "Spanish", "links": "http://www.megavideo.com/?v=H4ZILSZS", "temp": "2", "serie": "G", "epi": "14", "type": "VerOnline"},
{"lang": "Spanish", "links": "http://www.megaupload.com/?d=2K8K8WA0", "temp": "2", "serie": "G", "epi": "14", "type": "Descargar"},
{"lang": "Spanish", "links": "http://www.megaupload.com/?d=2K8K8WA0", "temp": "2", "serie": "G", "epi": "14", "type": "Descargar"},
{"lang": "Spanish", "links": "http://www.megavideo.com/?v=L34YE6NA", "temp": "2", "serie": "G", "epi": "13", "type": "VerOnline"},
{"lang": "Spanish", "links": "http://www.megavideo.com/?v=L34YE6NA", "temp": "2", "serie": "G", "epi": "13", "type": "VerOnline"},
{"lang": "Spanish", "links": "http://www.megaupload.com/?d=BG6GDTSN", "temp": "2", "serie": "G", "epi": "13", "type": "Descargar"},
{"lang": "Spanish", "links": "http://www.megaupload.com/?d=BG6GDTSN", "temp": "2", "serie": "G", "epi": "13", "type": "Descargar"},
{"lang": "Spanish", "links": "http://www.megavideo.com/?v=RWG7F9UR", "temp": "2", "serie": "G", "epi": "12", "type": "VerOnline"},
{"lang": "Spanish", "links": "http://www.megavideo.com/?v=RWG7F9UR", "temp": "2", "serie": "G", "epi": "12", "type": "VerOnline"},
{"lang": "Spanish", "links": "http://www.megaupload.com/?d=XUJMQ68S", "temp": "2", "serie": "G", "epi": "12", "type": "Descargar"},
{"lang": "Spanish", "links": "http://www.megaupload.com/?d=XUJMQ68S", "temp": "2", "serie": "G", "epi": "12", "type": "Descargar"},
{"lang": "Spanish", "links": "http://www.megavideo.com/?v=63RBP9P0", "temp": "2", "serie": "G", "epi": "11", "type": "VerOnline"},
{"lang": "Spanish", "links": "http://www.megavideo.com/?v=63RBP9P0", "temp": "2", "serie": "G", "epi": "11", "type": "VerOnline"},
{"lang": "Spanish", "links": "http://www.megaupload.com/?d=FDSMEME4", "temp": "2", "serie": "G", "epi": "11", "type": "Descargar"},
{"lang": "Spanish", "links": "http://www.megaupload.com/?d=FDSMEME4", "temp": "2", "serie": "G", "epi": "11", "type": "Descargar"},
{"lang": "Spanish", "links": "http://www.megavideo.com/?v=F5MS8Y7W", "temp": "2", "serie": "G", "epi": "10", "type": "VerOnline"},
{"lang": "Spanish", "links": "http://www.megavideo.com/?v=F5MS8Y7W", "temp": "2", "serie": "G", "epi": "10", "type": "VerOnline"},
{"lang": "Spanish", "links": "http://www.megaupload.com/?d=1MUCNDC1", "temp": "2", "serie": "G", "epi": "10", "type": "Descargar"},
{"lang": "Spanish", "links": "http://www.megaupload.com/?d=1MUCNDC1", "temp": "2", "serie": "G", "epi": "10", "type": "Descargar"},
{"lang": "Spanish", "links": "http://www.megavideo.com/?v=Z5XKP2FB", "temp": "2", "serie": "G", "epi": "09", "type": "VerOnline"},
{"lang": "Spanish", "links": "http://www.megavideo.com/?v=Z5XKP2FB", "temp": "2", "serie": "G", "epi": "09", "type": "VerOnline"},
{"lang": "Spanish", "links": "http://www.megaupload.com/?d=2DHTUE61", "temp": "2", "serie": "G", "epi": "09", "type": "Descargar"},
{"lang": "Spanish", "links": "http://www.megaupload.com/?d=2DHTUE61", "temp": "2", "serie": "G", "epi": "09", "type": "Descargar"},
{"lang": "Spanish", "links": "http://www.megavideo.com/?v=0UIM5WTL", "temp": "2", "serie": "G", "epi": "08", "type": "VerOnline"},
{"lang": "Spanish", "links": "http://www.megavideo.com/?v=0UIM5WTL", "temp": "2", "serie": "G", "epi": "08", "type": "VerOnline"},
{"lang": "Spanish", "links": "http://www.megaupload.com/?d=4A3Y8JAO", "temp": "2", "serie": "G", "epi": "08", "type": "Descargar"},
{"lang": "Spanish", "links": "http://www.megaupload.com/?d=4A3Y8JAO", "temp": "2", "serie": "G", "epi": "08", "type": "Descargar"},
{"lang": "Spanish", "links": "http://www.megavideo.com/?v=S6ETXDAF", "temp": "2", "serie": "G", "epi": "07", "type": "VerOnline"},
{"lang": "Spanish", "links": "http://www.megavideo.com/?v=S6ETXDAF", "temp": "2", "serie": "G", "epi": "07", "type": "VerOnline"},
{"lang": "Spanish", "links": "http://www.megaupload.com/?d=C04DEZA1", "temp": "2", "serie": "G", "epi": "07", "type": "Descargar"},
{"lang": "Spanish", "links": "http://www.megaupload.com/?d=C04DEZA1", "temp": "2", "serie": "G", "epi": "07", "type": "Descargar"},
{"lang": "Spanish", "links": "http://www.megavideo.com/?v=JA9ISBYX", "temp": "2", "serie": "G", "epi": "06", "type": "VerOnline"},
{"lang": "Spanish", "links": "http://www.megavideo.com/?v=JA9ISBYX", "temp": "2", "serie": "G", "epi": "06", "type": "VerOnline"},
{"lang": "Spanish", "links": "http://www.megaupload.com/?d=CND9QE6W", "temp": "2", "serie": "G", "epi": "06", "type": "Descargar"},
{"lang": "Spanish", "links": "http://www.megaupload.com/?d=CND9QE6W", "temp": "2", "serie": "G", "epi": "06", "type": "Descargar"},
{"lang": "Spanish", "links": "http://www.megavideo.com/?v=CC9SS6PG", "temp": "2", "serie": "G", "epi": "05", "type": "VerOnline"},
{"lang": "Spanish", "links": "http://www.megavideo.com/?v=CC9SS6PG", "temp": "2", "serie": "G", "epi": "05", "type": "VerOnline"},
{"lang": "Spanish", "links": "http://www.megaupload.com/?d=0MQ4RUT1", "temp": "2", "serie": "G", "epi": "05", "type": "Descargar"},
{"lang": "Spanish", "links": "http://www.megaupload.com/?d=0MQ4RUT1", "temp": "2", "serie": "G", "epi": "05", "type": "Descargar"},
{"lang": "Spanish", "links": "http://www.megavideo.com/?v=Z01FMRJ4", "temp": "2", "serie": "G", "epi": "04", "type": "VerOnline"},
{"lang": "Spanish", "links": "http://www.megavideo.com/?v=Z01FMRJ4", "temp": "2", "serie": "G", "epi": "04", "type": "VerOnline"},
{"lang": "Spanish", "links": "http://www.megaupload.com/?d=7WL5NS5Z", "temp": "2", "serie": "G", "epi": "04", "type": "Descargar"},
{"lang": "Spanish", "links": "http://www.megaupload.com/?d=7WL5NS5Z", "temp": "2", "serie": "G", "epi": "04", "type": "Descargar"},
{"lang": "Spanish", "links": "http://www.megavideo.com/?v=QFS5RMKX", "temp": "2", "serie": "G", "epi": "03", "type": "VerOnline"},
{"lang": "Spanish", "links": "http://www.megavideo.com/?v=QFS5RMKX", "temp": "2", "serie": "G", "epi": "03", "type": "VerOnline"},
{"lang": "Spanish", "links": "http://www.megaupload.com/?d=C1JX511P", "temp": "2", "serie": "G", "epi": "03", "type": "Descargar"},
{"lang": "Spanish", "links": "http://www.megaupload.com/?d=C1JX511P", "temp": "2", "serie": "G", "epi": "03", "type": "Descargar"},
{"lang": "Spanish", "links": "http://www.megavideo.com/?v=9LXFT777", "temp": "2", "serie": "G", "epi": "02", "type": "VerOnline"},
{"lang": "Spanish", "links": "http://www.megavideo.com/?v=9LXFT777", "temp": "2", "serie": "G", "epi": "02", "type": "VerOnline"},
{"lang": "Spanish", "links": "http://www.megaupload.com/?d=PI4BEO3N", "temp": "2", "serie": "G", "epi": "02", "type": "Descargar"},
{"lang": "Spanish", "links": "http://www.megaupload.com/?d=PI4BEO3N", "temp": "2", "serie": "G", "epi": "02", "type": "Descargar"},
{"lang": "Spanish", "links": "http://www.megavideo.com/?v=MYP55TAZ", "temp": "2", "serie": "G", "epi": "01", "type": "VerOnline"},
{"lang": "Spanish", "links": "http://www.megavideo.com/?v=MYP55TAZ", "temp": "2", "serie": "G", "epi": "01", "type": "VerOnline"},
{"lang": "Spanish", "links": "http://www.megaupload.com/?d=PI4BEO3N", "temp": "2", "serie": "G", "epi": "01", "type": "Descargar"},
{"lang": "Spanish", "links": "http://www.megaupload.com/?d=PI4BEO3N", "temp": "2", "serie": "G", "epi": "01", "type": "Descargar"},
{"lang": "Spanish", "links": "http://www.megavideo.com/?v=HEKVC2HL", "temp": "1", "serie": "G", "epi": "18", "type": "VerOnline"},
{"lang": "Spanish", "links": "http://www.megavideo.com/?v=HEKVC2HL", "temp": "1", "serie": "G", "epi": "18", "type": "VerOnline"},
{"lang": "Spanish", "links": "http://www.megaupload.com/?d=UHWJ8Q5X", "temp": "1", "serie": "G", "epi": "18", "type": "Descargar"},
{"lang": "Spanish", "links": "http://www.megaupload.com/?d=UHWJ8Q5X", "temp": "1", "serie": "G", "epi": "18", "type": "Descargar"},
{"lang": "Spanish", "links": "http://www.megavideo.com/?v=BDELQPMQ", "temp": "1", "serie": "G", "epi": "17", "type": "VerOnline"},
{"lang": "Spanish", "links": "http://www.megavideo.com/?v=BDELQPMQ", "temp": "1", "serie": "G", "epi": "17", "type": "VerOnline"},
{"lang": "Spanish", "links": "http://www.megaupload.com/?d=6NKSLKNC", "temp": "1", "serie": "G", "epi": "17", "type": "Descargar"},
{"lang": "Spanish", "links": "http://www.megaupload.com/?d=6NKSLKNC", "temp": "1", "serie": "G", "epi": "17", "type": "Descargar"},
{"lang": "Spanish", "links": "http://www.megavideo.com/?v=U8I9TMCR", "temp": "1", "serie": "G", "epi": "16", "type": "VerOnline"},
{"lang": "Spanish", "links": "http://www.megavideo.com/?v=U8I9TMCR", "temp": "1", "serie": "G", "epi": "16", "type": "VerOnline"},
{"lang": "Spanish", "links": "http://www.megaupload.com/?d=ZIYR1ZNF", "temp": "1", "serie": "G", "epi": "16", "type": "Descargar"},
{"lang": "Spanish", "links": "http://www.megaupload.com/?d=ZIYR1ZNF", "temp": "1", "serie": "G", "epi": "16", "type": "Descargar"},
{"lang": "Spanish", "links": "http://www.megavideo.com/?v=G60GDVOE", "temp": "1", "serie": "G", "epi": "15", "type": "VerOnline"},
{"lang": "Spanish", "links": "http://www.megavideo.com/?v=G60GDVOE", "temp": "1", "serie": "G", "epi": "15", "type": "VerOnline"},
{"lang": "Spanish", "links": "http://www.megaupload.com/?d=9S2FPX97", "temp": "1", "serie": "G", "epi": "15", "type": "Descargar"},
{"lang": "Spanish", "links": "http://www.megaupload.com/?d=9S2FPX97", "temp": "1", "serie": "G", "epi": "15", "type": "Descargar"},
{"lang": "Spanish", "links": "http://www.megavideo.com/?v=HK4EG5L3", "temp": "1", "serie": "G", "epi": "14", "type": "VerOnline"},
{"lang": "Spanish", "links": "http://www.megavideo.com/?v=HK4EG5L3", "temp": "1", "serie": "G", "epi": "14", "type": "VerOnline"},
{"lang": "Spanish", "links": "http://www.megaupload.com/?d=ZC2V9RH0", "temp": "1", "serie": "G", "epi": "14", "type": "Descargar"},
{"lang": "Spanish", "links": "http://www.megaupload.com/?d=ZC2V9RH0", "temp": "1", "serie": "G", "epi": "14", "type": "Descargar"},
{"lang": "Spanish", "links": "http://www.megavideo.com/?v=ELCGP0ZA", "temp": "1", "serie": "G", "epi": "13", "type": "VerOnline"},
{"lang": "Spanish", "links": "http://www.megavideo.com/?v=ELCGP0ZA", "temp": "1", "serie": "G", "epi": "13", "type": "VerOnline"},
{"lang": "Spanish", "links": "http://www.megaupload.com/?d=TZ4LC94A", "temp": "1", "serie": "G", "epi": "13", "type": "Descargar"},
{"lang": "Spanish", "links": "http://www.megaupload.com/?d=TZ4LC94A", "temp": "1", "serie": "G", "epi": "13", "type": "Descargar"},
{"lang": "Spanish", "links": "http://www.megavideo.com/?v=YXY7V5JY", "temp": "1", "serie": "G", "epi": "12", "type": "VerOnline"},
{"lang": "Spanish", "links": "http://www.megavideo.com/?v=YXY7V5JY", "temp": "1", "serie": "G", "epi": "12", "type": "VerOnline"},
{"lang": "Spanish", "links": "http://www.megaupload.com/?d=N5TBIZYY", "temp": "1", "serie": "G", "epi": "12", "type": "Descargar"},
{"lang": "Spanish", "links": "http://www.megaupload.com/?d=N5TBIZYY", "temp": "1", "serie": "G", "epi": "12", "type": "Descargar"},
{"lang": "Spanish", "links": "http://www.megavideo.com/?v=88HAQB82", "temp": "1", "serie": "G", "epi": "11", "type": "VerOnline"},
{"lang": "Spanish", "links": "http://www.megavideo.com/?v=88HAQB82", "temp": "1", "serie": "G", "epi": "11", "type": "VerOnline"},
{"lang": "Spanish", "links": "http://www.megaupload.com/?d=HUVGCQF5", "temp": "1", "serie": "G", "epi": "11", "type": "Descargar"},
{"lang": "Spanish", "links": "http://www.megaupload.com/?d=HUVGCQF5", "temp": "1", "serie": "G", "epi": "11", "type": "Descargar"},
{"lang": "Spanish", "links": "http://www.megavideo.com/?v=2NWH3A9G", "temp": "1", "serie": "G", "epi": "10", "type": "VerOnline"},
{"lang": "Spanish", "links": "http://www.megavideo.com/?v=2NWH3A9G", "temp": "1", "serie": "G", "epi": "10", "type": "VerOnline"},
{"lang": "Spanish", "links": "http://www.megaupload.com/?d=D47OMND1", "temp": "1", "serie": "G", "epi": "10", "type": "Descargar"},
{"lang": "Spanish", "links": "http://www.megaupload.com/?d=D47OMND1", "temp": "1", "serie": "G", "epi": "10", "type": "Descargar"},
{"lang": "Spanish", "links": "http://www.megavideo.com/?v=Q6JX7EIV", "temp": "1", "serie": "G", "epi": "09", "type": "VerOnline"},
{"lang": "Spanish", "links": "http://www.megavideo.com/?v=Q6JX7EIV", "temp": "1", "serie": "G", "epi": "09", "type": "VerOnline"},
{"lang": "Spanish", "links": "http://www.megaupload.com/?d=W4RXI0ZV", "temp": "1", "serie": "G", "epi": "09", "type": "Descargar"},
{"lang": "Spanish", "links": "http://www.megaupload.com/?d=W4RXI0ZV", "temp": "1", "serie": "G", "epi": "09", "type": "Descargar"},
{"lang": "Spanish", "links": "http://www.megavideo.com/?v=NXLOZW7K", "temp": "1", "serie": "G", "epi": "08", "type": "VerOnline"},
{"lang": "Spanish", "links": "http://www.megavideo.com/?v=NXLOZW7K", "temp": "1", "serie": "G", "epi": "08", "type": "VerOnline"},
{"lang": "Spanish", "links": "http://www.megaupload.com/?d=7KAFVP2C", "temp": "1", "serie": "G", "epi": "08", "type": "Descargar"},
{"lang": "Spanish", "links": "http://www.megaupload.com/?d=7KAFVP2C", "temp": "1", "serie": "G", "epi": "08", "type": "Descargar"},
{"lang": "Spanish", "links": "http://www.megavideo.com/?v=PP3ZM83I", "temp": "1", "serie": "G", "epi": "07", "type": "VerOnline"},
{"lang": "Spanish", "links": "http://www.megavideo.com/?v=PP3ZM83I", "temp": "1", "serie": "G", "epi": "07", "type": "VerOnline"},
{"lang": "Spanish", "links": "http://www.megaupload.com/?d=BAKU0XVQ", "temp": "1", "serie": "G", "epi": "07", "type": "Descargar"},
{"lang": "Spanish", "links": "http://www.megaupload.com/?d=BAKU0XVQ", "temp": "1", "serie": "G", "epi": "07", "type": "Descargar"},
{"lang": "Spanish", "links": "http://www.megavideo.com/?v=XHTIAI2T", "temp": "1", "serie": "G", "epi": "06", "type": "VerOnline"},
{"lang": "Spanish", "links": "http://www.megavideo.com/?v=XHTIAI2T", "temp": "1", "serie": "G", "epi": "06", "type": "VerOnline"},
{"lang": "Spanish", "links": "http://www.megaupload.com/?d=RKPH6WWD", "temp": "1", "serie": "G", "epi": "06", "type": "Descargar"},
{"lang": "Spanish", "links": "http://www.megaupload.com/?d=RKPH6WWD", "temp": "1", "serie": "G", "epi": "06", "type": "Descargar"},
{"lang": "Spanish", "links": "http://www.megavideo.com/?v=YVLSS6JM", "temp": "1", "serie": "G", "epi": "05", "type": "VerOnline"},
{"lang": "Spanish", "links": "http://www.megavideo.com/?v=YVLSS6JM", "temp": "1", "serie": "G", "epi": "05", "type": "VerOnline"},
{"lang": "Spanish", "links": "http://www.megaupload.com/?d=8G6TDZHX", "temp": "1", "serie": "G", "epi": "05", "type": "Descargar"},
{"lang": "Spanish", "links": "http://www.megaupload.com/?d=8G6TDZHX", "temp": "1", "serie": "G", "epi": "05", "type": "Descargar"},
{"lang": "Spanish", "links": "http://www.megavideo.com/?v=IXJ8YGT5", "temp": "1", "serie": "G", "epi": "04", "type": "VerOnline"},
{"lang": "Spanish", "links": "http://www.megavideo.com/?v=IXJ8YGT5", "temp": "1", "serie": "G", "epi": "04", "type": "VerOnline"},
{"lang": "Spanish", "links": "http://www.megaupload.com/?d=Y7FZMCLG", "temp": "1", "serie": "G", "epi": "04", "type": "Descargar"},
{"lang": "Spanish", "links": "http://www.megaupload.com/?d=Y7FZMCLG", "temp": "1", "serie": "G", "epi": "04", "type": "Descargar"},
{"lang": "Spanish", "links": "http://www.megavideo.com/?v=EOH72C7V", "temp": "1", "serie": "G", "epi": "03", "type": "VerOnline"},
{"lang": "Spanish", "links": "http://www.megavideo.com/?v=EOH72C7V", "temp": "1", "serie": "G", "epi": "03", "type": "VerOnline"},
{"lang": "Spanish", "links": "http://www.megaupload.com/?d=1KOJRKUY", "temp": "1", "serie": "G", "epi": "03", "type": "Descargar"},
{"lang": "Spanish", "links": "http://www.megaupload.com/?d=1KOJRKUY", "temp": "1", "serie": "G", "epi": "03", "type": "Descargar"},
{"lang": "Spanish", "links": "http://www.megavideo.com/?v=S9LC7EUI", "temp": "1", "serie": "G", "epi": "01", "type": "VerOnline"},
{"lang": "Spanish", "links": "http://www.megavideo.com/?v=S9LC7EUI", "temp": "1", "serie": "G", "epi": "01", "type": "VerOnline"},
{"lang": "Spanish", "links": "http://www.megaupload.com/?d=ACOLHXNF", "temp": "1", "serie": "G", "epi": "01", "type": "Descargar"},
{"lang": "Spanish", "links": "http://www.megaupload.com/?d=ACOLHXNF", "temp": "1", "serie": "G", "epi": "01", "type": "Descargar"},
{"lang": "English", "links": "http://www.megavideo.com/?v=S14RUL6Y", "temp": "2", "serie": "G", "epi": "02", "type": "VerOnline", "sublang": "Spanish"},
{"lang": "English", "links": "http://www.megavideo.com/?v=7KF3GA70", "temp": "2", "serie": "G", "epi": "02", "type": "VerOnline", "sublang": "Spanish"},
{"lang": "English", "links": "http://www.megaupload.com/?d=W4ZNJ1DN", "temp": "2", "serie": "G", "epi": "02", "type": "Descargar", "sublang": "Spanish"},
{"lang": "English", "links": "http://www.megaupload.com/?d=W4ZNJ1DN", "temp": "2", "serie": "G", "epi": "02", "type": "Descargar", "sublang": "Spanish"},
{"lang": "English", "links": "http://www.megavideo.com/?v=KACH0FIF", "temp": "2", "serie": "G", "epi": "01", "type": "VerOnline", "sublang": "Spanish"},
{"lang": "English", "links": "http://www.megavideo.com/?v=KACH0FIF", "temp": "2", "serie": "G", "epi": "01", "type": "VerOnline", "sublang": "Spanish"},
{"lang": "English", "links": "http://www.megaupload.com/?d=N225R3CK", "temp": "2", "serie": "G", "epi": "01", "type": "Descargar", "sublang": "Spanish"},
{"lang": "English", "links": "http://www.megaupload.com/?d=N225R3CK", "temp": "2", "serie": "G", "epi": "01", "type": "Descargar", "sublang": "Spanish"},
{"lang": "Spanish", "links": "http://www.megavideo.com/?v=5D6TZLOA", "temp": "1", "serie": "G", "epi": "22", "type": "VerOnline"},
{"lang": "Spanish", "links": "http://www.megavideo.com/?v=5D6TZLOA", "temp": "1", "serie": "G", "epi": "22", "type": "VerOnline"},
{"lang": "Spanish", "links": "http://www.megaupload.com/?d=VGZBASPQ", "temp": "1", "serie": "G", "epi": "22", "type": "Descargar"},
{"lang": "Spanish", "links": "http://www.megaupload.com/?d=VGZBASPQ", "temp": "1", "serie": "G", "epi": "22", "type": "Descargar"},
{"lang": "Spanish", "links": "http://www.megavideo.com/?v=O7MKSTNA", "temp": "1", "serie": "G", "epi": "21", "type": "VerOnline"},
{"lang": "English", "links": "http://www.megavideo.com/?d=T6NSFU0O", "temp": "1", "serie": "G", "epi": "21", "type": "VerOnline", "sublang": "Spanish"},
{"lang": "Spanish", "links": "http://www.megaupload.com/?d=4KU1MU5B", "temp": "1", "serie": "G", "epi": "21", "type": "Descargar"},
{"lang": "English", "links": "http://www.megaupload.com/?d=T6NSFU0O", "temp": "1", "serie": "G", "epi": "21", "type": "Descargar", "sublang": "Spanish"},
{"lang": "Spanish", "links": "http://www.megavideo.com/?v=S4E8U3LS", "temp": "1", "serie": "G", "epi": "20", "type": "VerOnline"},
{"lang": "English", "links": "http://www.megavideo.com/?v=6T44HMCV", "temp": "1", "serie": "G", "epi": "20", "type": "VerOnline", "sublang": "Spanish"},
{"lang": "Spanish", "links": "http://www.megaupload.com/?d=GV1SSYT5", "temp": "1", "serie": "G", "epi": "20", "type": "Descargar"},
{"lang": "English", "links": "http://www.megaupload.com/?d=JY8C4AK", "temp": "1", "serie": "G", "epi": "20", "type": "Descargar", "sublang": "Spanish"},
{"lang": "Spanish", "links": "http://www.megavideo.com/?v=BVAFCS5R", "temp": "1", "serie": "G", "epi": "19", "type": "VerOnline"},
{"lang": "Spanish", "links": "http://www.megavideo.com/?v=BVAFCS5R", "temp": "1", "serie": "G", "epi": "19", "type": "VerOnline"},
{"lang": "Spanish", "links": "http://www.megaupload.com/?d=FEMR3P6K", "temp": "1", "serie": "G", "epi": "19", "type": "Descargar"},
{"lang": "Spanish", "links": "http://www.megaupload.com/?d=FEMR3P6K", "temp": "1", "serie": "G", "epi": "19", "type": "Descargar"},
{"lang": "Spanish", "links": "http://www.megavideo.com/?v=7HKAX0I5", "temp": "1", "serie": "G", "epi": "18", "type": "VerOnline"},
{"lang": "Spanish", "links": "http://www.megavideo.com/?v=7HKAX0I5", "temp": "1", "serie": "G", "epi": "18", "type": "VerOnline"},
{"lang": "Spanish", "links": "http://www.megaupload.com/?d=CDDF6EUS", "temp": "1", "serie": "G", "epi": "18", "type": "Descargar"},
{"lang": "Spanish", "links": "http://www.megaupload.com/?d=CDDF6EUS", "temp": "1", "serie": "G", "epi": "18", "type": "Descargar"},
{"lang": "Spanish", "links": "http://www.megavideo.com/?v=BX6HUDOT", "temp": "1", "serie": "G", "epi": "17", "type": "VerOnline"},
{"lang": "Spanish", "links": "http://www.megavideo.com/?v=BX6HUDOT", "temp": "1", "serie": "G", "epi": "17", "type": "VerOnline"},
{"lang": "Spanish", "links": "http://www.megaupload.com/?d=O9XYYJ6R", "temp": "1", "serie": "G", "epi": "17", "type": "Descargar"},
{"lang": "Spanish", "links": "http://www.megaupload.com/?d=O9XYYJ6R", "temp": "1", "serie": "G", "epi": "17", "type": "Descargar"},
{"lang": "Spanish", "links": "http://www.megavideo.com/?v=UM6D4FYW", "temp": "1", "serie": "G", "epi": "16", "type": "VerOnline"},
{"lang": "Spanish", "links": "http://www.megavideo.com/?v=UM6D4FYW", "temp": "1", "serie": "G", "epi": "16", "type": "VerOnline"},
{"lang": "Spanish", "links": "http://www.megaupload.com/?d=VA6TU65H", "temp": "1", "serie": "G", "epi": "16", "type": "Descargar"},
{"lang": "Spanish", "links": "http://www.megaupload.com/?d=VA6TU65H", "temp": "1", "serie": "G", "epi": "16", "type": "Descargar"},
{"lang": "Spanish", "links": "http://www.megavideo.com/?v=RL08Y7U3", "temp": "1", "serie": "G", "epi": "15", "type": "VerOnline"},
{"lang": "Spanish", "links": "http://www.megavideo.com/?v=RL08Y7U3", "temp": "1", "serie": "G", "epi": "15", "type": "VerOnline"},
{"lang": "Spanish", "links": "http://www.megaupload.com/?d=DSB1R5NZ", "temp": "1", "serie": "G", "epi": "15", "type": "Descargar"},
{"lang": "Spanish", "links": "http://www.megaupload.com/?d=DSB1R5NZ", "temp": "1", "serie": "G", "epi": "15", "type": "Descargar"},
{"lang": "Spanish", "links": "http://www.megavideo.com/?v=YOJRR6RB", "temp": "1", "serie": "G", "epi": "14", "type": "VerOnline"},
{"lang": "Spanish", "links": "http://www.megavideo.com/?v=YOJRR6RB", "temp": "1", "serie": "G", "epi": "14", "type": "VerOnline"},
{"lang": "Spanish", "links": "http://www.megaupload.com/?d=L8Z881WC", "temp": "1", "serie": "G", "epi": "14", "type": "Descargar"},
{"lang": "Spanish", "links": "http://www.megaupload.com/?d=L8Z881WC", "temp": "1", "serie": "G", "epi": "14", "type": "Descargar"},
{"lang": "Spanish", "links": "http://www.megavideo.com/?v=M0N1JMMM", "temp": "1", "serie": "G", "epi": "13", "type": "VerOnline"},
{"lang": "Spanish", "links": "http://www.megavideo.com/?v=M0N1JMMM", "temp": "1", "serie": "G", "epi": "13", "type": "VerOnline"},
{"lang": "Spanish", "links": "http://www.megaupload.com/?d=EUWF3LTK", "temp": "1", "serie": "G", "epi": "13", "type": "Descargar"},
{"lang": "Spanish", "links": "http://www.megaupload.com/?d=EUWF3LTK", "temp": "1", "serie": "G", "epi": "13", "type": "Descargar"},
{"lang": "Spanish", "links": "http://www.megavideo.com/?v=SZW71YRY", "temp": "1", "serie": "G", "epi": "12", "type": "VerOnline"},
{"lang": "Spanish", "links": "http://www.megavideo.com/?v=SZW71YRY", "temp": "1", "serie": "G", "epi": "12", "type": "VerOnline"},
{"lang": "Spanish", "links": "http://www.megaupload.com/?d=DWDVV570", "temp": "1", "serie": "G", "epi": "12", "type": "Descargar"},
{"lang": "Spanish", "links": "http://www.megaupload.com/?d=DWDVV570", "temp": "1", "serie": "G", "epi": "12", "type": "Descargar"},
{"lang": "Spanish", "links": "http://www.megavideo.com/?v=M2SSB8LH", "temp": "1", "serie": "G", "epi": "11", "type": "VerOnline"},
{"lang": "Spanish", "links": "http://www.megavideo.com/?v=M2SSB8LH", "temp": "1", "serie": "G", "epi": "11", "type": "VerOnline"},
{"lang": "Spanish", "links": "http://www.megaupload.com/?d=4SW5AHJ7", "temp": "1", "serie": "G", "epi": "11", "type": "Descargar"},
{"lang": "Spanish", "links": "http://www.megaupload.com/?d=4SW5AHJ7", "temp": "1", "serie": "G", "epi": "11", "type": "Descargar"},
{"lang": "Spanish", "links": "http://www.megavideo.com/?v=V4Y15I6A", "temp": "1", "serie": "G", "epi": "10", "type": "VerOnline"},
{"lang": "Spanish", "links": "http://www.megavideo.com/?v=V4Y15I6A", "temp": "1", "serie": "G", "epi": "10", "type": "VerOnline"},
{"lang": "Spanish", "links": "http://www.megaupload.com/?d=SQRBUYD2", "temp": "1", "serie": "G", "epi": "10", "type": "Descargar"},
{"lang": "Spanish", "links": "http://www.megaupload.com/?d=SQRBUYD2", "temp": "1", "serie": "G", "epi": "10", "type": "Descargar"},
{"lang": "Spanish", "links": "http://www.megavideo.com/?v=XYMIQ6XL", "temp": "1", "serie": "G", "epi": "09", "type": "VerOnline"},
{"lang": "Spanish", "links": "http://www.megavideo.com/?v=XYMIQ6XL", "temp": "1", "serie": "G", "epi": "09", "type": "VerOnline"},
{"lang": "Spanish", "links": "http://www.megaupload.com/?d=P5PKCO4M", "temp": "1", "serie": "G", "epi": "09", "type": "Descargar"},
{"lang": "Spanish", "links": "http://www.megaupload.com/?d=P5PKCO4M", "temp": "1", "serie": "G", "epi": "09", "type": "Descargar"},
{"lang": "Spanish", "links": "http://www.megavideo.com/?v=JX44IQC9", "temp": "1", "serie": "G", "epi": "08", "type": "VerOnline"},
{"lang": "Spanish", "links": "http://www.megavideo.com/?v=JX44IQC9", "temp": "1", "serie": "G", "epi": "08", "type": "VerOnline"},
{"lang": "Spanish", "links": "http://www.megaupload.com/?d=HQ2UW3B8", "temp": "1", "serie": "G", "epi": "08", "type": "Descargar"},
{"lang": "Spanish", "links": "http://www.megaupload.com/?d=HQ2UW3B8", "temp": "1", "serie": "G", "epi": "08", "type": "Descargar"},
{"lang": "Spanish", "links": "http://www.megavideo.com/?v=FKX9W1WN", "temp": "1", "serie": "G", "epi": "07", "type": "VerOnline"},
{"lang": "Spanish", "links": "http://www.megavideo.com/?v=FKX9W1WN", "temp": "1", "serie": "G", "epi": "07", "type": "VerOnline"},
{"lang": "Spanish", "links": "http://www.megaupload.com/?d=HIUACRUL", "temp": "1", "serie": "G", "epi": "07", "type": "Descargar"},
{"lang": "Spanish", "links": "http://www.megaupload.com/?d=HIUACRUL", "temp": "1", "serie": "G", "epi": "07", "type": "Descargar"},
{"lang": "Spanish", "links": "http://www.megavideo.com/?v=C54N5AJG", "temp": "1", "serie": "G", "epi": "06", "type": "VerOnline"},
{"lang": "Spanish", "links": "http://www.megavideo.com/?v=C54N5AJG", "temp": "1", "serie": "G", "epi": "06", "type": "VerOnline"},
{"lang": "Spanish", "links": "http://www.megaupload.com/?d=E9ZN0FP2", "temp": "1", "serie": "G", "epi": "06", "type": "Descargar"},
{"lang": "Spanish", "links": "http://www.megaupload.com/?d=E9ZN0FP2", "temp": "1", "serie": "G", "epi": "06", "type": "Descargar"},
{"lang": "Spanish", "links": "http://www.megavideo.com/?d=5ACFHK7K", "temp": "1", "serie": "G", "epi": "05", "type": "VerOnline"},
{"lang": "Spanish", "links": "http://www.megavideo.com/?d=5ACFHK7K", "temp": "1", "serie": "G", "epi": "05", "type": "VerOnline"},
{"lang": "Spanish", "links": "http://www.megaupload.com/?d=5ACFHK7K", "temp": "1", "serie": "G", "epi": "05", "type": "Descargar"},
{"lang": "Spanish", "links": "http://www.megaupload.com/?d=5ACFHK7K", "temp": "1", "serie": "G", "epi": "05", "type": "Descargar"},
{"lang": "Spanish", "links": "http://www.megavideo.com/?v=WQ14LE14", "temp": "1", "serie": "G", "epi": "04", "type": "VerOnline"},
{"lang": "Spanish", "links": "http://www.megavideo.com/?v=WQ14LE14", "temp": "1", "serie": "G", "epi": "04", "type": "VerOnline"},
{"lang": "Spanish", "links": "http://www.megaupload.com/?d=0JAXI0NM", "temp": "1", "serie": "G", "epi": "04", "type": "Descargar"},
{"lang": "Spanish", "links": "http://www.megaupload.com/?d=0JAXI0NM", "temp": "1", "serie": "G", "epi": "04", "type": "Descargar"},
{"lang": "Spanish", "links": "http://www.megavideo.com/?v=IGQHZH4U", "temp": "1", "serie": "G", "epi": "03", "type": "VerOnline"},
{"lang": "Spanish", "links": "http://www.megavideo.com/?v=IGQHZH4U", "temp": "1", "serie": "G", "epi": "03", "type": "VerOnline"},
{"lang": "Spanish", "links": "http://www.megaupload.com/?d=MKNVJPF0", "temp": "1", "serie": "G", "epi": "03", "type": "Descargar"},
{"lang": "Spanish", "links": "http://www.megaupload.com/?d=MKNVJPF0", "temp": "1", "serie": "G", "epi": "03", "type": "Descargar"},
{"lang": "Spanish", "links": "http://www.megavideo.com/?v=3WVZUB40", "temp": "1", "serie": "G", "epi": "02", "type": "VerOnline"},
{"lang": "Spanish", "links": "http://www.megavideo.com/?v=3WVZUB40", "temp": "1", "serie": "G", "epi": "02", "type": "VerOnline"},
{"lang": "Spanish", "links": "http://www.megaupload.com/?d=ROBEWMZV", "temp": "1", "serie": "G", "epi": "02", "type": "Descargar"},
{"lang": "Spanish", "links": "http://www.megaupload.com/?d=ROBEWMZV", "temp": "1", "serie": "G", "epi": "02", "type": "Descargar"}]